subplots_from_axsize/__init__.py
subplots_from_axsize/_subplots_from_axsize.py
subplots_from_axsize-0.1.9.dist-info/LICENSE
subplots_from_axsize-0.1.9.dist-info/METADATA
subplots_from_axsize-0.1.9.dist-info/WHEEL
subplots_from_axsize-0.1.9.dist-info/RECORD
