Metadata-Version: 2.1
Name: subplots-from-axsize
Version: 0.1.9
Summary: 
Author: Frederic Grabowski
Author-email: grabowski.frederic@gmail.com
Requires-Python: >=3.8,<4.0
Classifier: Programming Language :: Python :: 3
Classifier: Programming Language :: Python :: 3.8
Classifier: Programming Language :: Python :: 3.9
Classifier: Programming Language :: Python :: 3.10
Classifier: Programming Language :: Python :: 3.11
Requires-Dist: matplotlib (>=3.5,<4.0)
